malbook/__init__.py
malbook/__main__.py
malbook/environment.py
malbook/errors.py
malbook/framework.py
malbook-1.0.0.dist-info/LICENSE
malbook-1.0.0.dist-info/METADATA
malbook-1.0.0.dist-info/WHEEL
malbook-1.0.0.dist-info/entry_points.txt
malbook-1.0.0.dist-info/top_level.txt
malbook-1.0.0.dist-info/RECORD
